{
  "8eab665a977f60e9478330cd577795865cb25bfa": {
    "title": "This Couple Quit Their 9-5 To Work On A Floating Pizzeria In The Caribbean",
    "url": "https://www.delish.com/food/a66069056/pizza-pi-floating-caribbean-restaurant/",
    "category": "test/3general",
    "subcategory": "3General",
    "created": "2025-09-18"
  },
  "2b4c9446bd6bb992161985a2b12407a2172dd047": {
    "title": "Chicken Parmesan",
    "url": "https://www.delish.com/cooking/recipe-ideas/a51451/easy-chicken-parmesan-recipe/",
    "category": "test/3general",
    "subcategory": "3General",
    "created": "2025-09-18"
  },
  "22f57c8c5476b0824d6d3ad4eb8e3de460081952": {
    "title": "Guava Margaritas",
    "url": "https://www.tasteofhome.com/recipes/guava-margaritas/",
    "category": "test/4general",
    "subcategory": "4General",
    "created": "2025-09-18"
  },
  "3f4db5911348758963011d7f8b63beb8bb9c76b1": {
    "title": "Muffaletta Dip",
    "url": "https://www.tasteofhome.com/recipes/muffaletta-dip/",
    "category": "test/4general",
    "subcategory": "4General",
    "created": "2025-09-18"
  }
}